edc_blood_results/__init__.py
edc_blood_results/action_items.py
edc_blood_results/apps.py
edc_blood_results/constants.py
edc_blood_results/fieldsets.py
edc_blood_results/models.py
edc_blood_results/admin/__init__.py
edc_blood_results/admin/blood_results_modeladmin_mixin.py
edc_blood_results/form_validator_mixins/__init__.py
edc_blood_results/form_validator_mixins/blood_results_fbg_form_validator_mixin.py
edc_blood_results/form_validator_mixins/blood_results_form_validator_mixin.py
edc_blood_results/form_validator_mixins/blood_results_glu_form_validator_mixin.py
edc_blood_results/model_mixins/__init__.py
edc_blood_results/model_mixins/blood_result_model_mixin.py
edc_blood_results/model_mixins/fbc_model_mixins.py
edc_blood_results/model_mixins/fbg_model_mixin.py
edc_blood_results/model_mixins/glucose_model_mixin.py
edc_blood_results/model_mixins/hba1c_model_mixin.py
edc_blood_results/model_mixins/insulin_model_mixin.py
edc_blood_results/model_mixins/lft_model_mixins.py
edc_blood_results/model_mixins/lipid_model_mixins.py
edc_blood_results/model_mixins/rft_model_mixins.py
edc_blood_results/tests/__init__.py
edc_blood_results/tests/admin.py
edc_blood_results/tests/forms.py
edc_blood_results/tests/lab_profiles.py
edc_blood_results/tests/models.py
edc_blood_results/tests/test_case_mixin.py
edc_blood_results/tests/urls.py
edc_blood_results/tests/visit_schedule.py
edc_blood_results/tests/tests/__init__.py
edc_blood_results/tests/tests/test_blood_result.py
edc_blood_results/tests/tests/test_form.py
edc_blood_results-0.1.17.dist-info/LICENSE
edc_blood_results-0.1.17.dist-info/METADATA
edc_blood_results-0.1.17.dist-info/WHEEL
edc_blood_results-0.1.17.dist-info/top_level.txt
edc_blood_results-0.1.17.dist-info/RECORD
